/* XXX AUTOMATICALLY GENERATED FILE -- DO NOT EDIT */
    { /* 0 */ "nop", instr_nop },
    { /* 1 */ "aconst_null", instr_aconst_null },
    { /* 2 */ "iconst_m1", instr_iconst_m1 },
    { /* 3 */ "iconst_0", instr_iconst_0 },
    { /* 4 */ "iconst_1", instr_iconst_1 },
    { /* 5 */ "iconst_2", instr_iconst_2 },
    { /* 6 */ "iconst_3", instr_iconst_3 },
    { /* 7 */ "iconst_4", instr_iconst_4 },
    { /* 8 */ "iconst_5", instr_iconst_5 },
    { /* 9 */ "lconst_0", instr_lconst_0 },
    { /* 10 */ "lconst_1", instr_lconst_1 },
    { /* 11 */ "fconst_0", instr_fconst_0 },
    { /* 12 */ "fconst_1", instr_fconst_1 },
    { /* 13 */ "fconst_2", instr_fconst_2 },
    { /* 14 */ "dconst_0", instr_dconst_0 },
    { /* 15 */ "dconst_1", instr_dconst_1 },
    { /* 16 */ "bipush", instr_bipush },
    { /* 17 */ "sipush", instr_sipush },
    { /* 18 */ "ldc", instr_ldc },
    { /* 19 */ "ldc_w", instr_ldc_w },
    { /* 20 */ "ldc2_w", instr_ldc2_w },
    { /* 21 */ "iload", instr_iload },
    { /* 22 */ "lload", instr_lload },
    { /* 23 */ "fload", instr_fload },
    { /* 24 */ "dload", instr_dload },
    { /* 25 */ "aload", instr_aload },
    { /* 26 */ "iload_0", instr_iload_0 },
    { /* 27 */ "iload_1", instr_iload_1 },
    { /* 28 */ "iload_2", instr_iload_2 },
    { /* 29 */ "iload_3", instr_iload_3 },
    { /* 30 */ "lload_0", instr_lload_0 },
    { /* 31 */ "lload_1", instr_lload_1 },
    { /* 32 */ "lload_2", instr_lload_2 },
    { /* 33 */ "lload_3", instr_lload_3 },
    { /* 34 */ "fload_0", instr_fload_0 },
    { /* 35 */ "fload_1", instr_fload_1 },
    { /* 36 */ "fload_2", instr_fload_2 },
    { /* 37 */ "fload_3", instr_fload_3 },
    { /* 38 */ "dload_0", instr_dload_0 },
    { /* 39 */ "dload_1", instr_dload_1 },
    { /* 40 */ "dload_2", instr_dload_2 },
    { /* 41 */ "dload_3", instr_dload_3 },
    { /* 42 */ "aload_0", instr_aload_0 },
    { /* 43 */ "aload_1", instr_aload_1 },
    { /* 44 */ "aload_2", instr_aload_2 },
    { /* 45 */ "aload_3", instr_aload_3 },
    { /* 46 */ "iaload", instr_iaload },
    { /* 47 */ "laload", instr_laload },
    { /* 48 */ "faload", instr_faload },
    { /* 49 */ "daload", instr_daload },
    { /* 50 */ "aaload", instr_aaload },
    { /* 51 */ "baload", instr_baload },
    { /* 52 */ "caload", instr_caload },
    { /* 53 */ "saload", instr_saload },
    { /* 54 */ "istore", instr_istore },
    { /* 55 */ "lstore", instr_lstore },
    { /* 56 */ "fstore", instr_fstore },
    { /* 57 */ "dstore", instr_dstore },
    { /* 58 */ "astore", instr_astore },
    { /* 59 */ "istore_0", instr_istore_0 },
    { /* 60 */ "istore_1", instr_istore_1 },
    { /* 61 */ "istore_2", instr_istore_2 },
    { /* 62 */ "istore_3", instr_istore_3 },
    { /* 63 */ "lstore_0", instr_lstore_0 },
    { /* 64 */ "lstore_1", instr_lstore_1 },
    { /* 65 */ "lstore_2", instr_lstore_2 },
    { /* 66 */ "lstore_3", instr_lstore_3 },
    { /* 67 */ "fstore_0", instr_fstore_0 },
    { /* 68 */ "fstore_1", instr_fstore_1 },
    { /* 69 */ "fstore_2", instr_fstore_2 },
    { /* 70 */ "fstore_3", instr_fstore_3 },
    { /* 71 */ "dstore_0", instr_dstore_0 },
    { /* 72 */ "dstore_1", instr_dstore_1 },
    { /* 73 */ "dstore_2", instr_dstore_2 },
    { /* 74 */ "dstore_3", instr_dstore_3 },
    { /* 75 */ "astore_0", instr_astore_0 },
    { /* 76 */ "astore_1", instr_astore_1 },
    { /* 77 */ "astore_2", instr_astore_2 },
    { /* 78 */ "astore_3", instr_astore_3 },
    { /* 79 */ "iastore", instr_iastore },
    { /* 80 */ "lastore", instr_lastore },
    { /* 81 */ "fastore", instr_fastore },
    { /* 82 */ "dastore", instr_dastore },
    { /* 83 */ "aastore", instr_aastore },
    { /* 84 */ "bastore", instr_bastore },
    { /* 85 */ "castore", instr_castore },
    { /* 86 */ "sastore", instr_sastore },
    { /* 87 */ "pop", instr_pop },
    { /* 88 */ "pop2", instr_pop2 },
    { /* 89 */ "dup", instr_dup },
    { /* 90 */ "dup_x1", instr_dup_x1 },
    { /* 91 */ "dup_x2", instr_dup_x2 },
    { /* 92 */ "dup2", instr_dup2 },
    { /* 93 */ "dup2_x1", instr_dup2_x1 },
    { /* 94 */ "dup2_x2", instr_dup2_x2 },
    { /* 95 */ "swap", instr_swap },
    { /* 96 */ "iadd", instr_iadd },
    { /* 97 */ "ladd", instr_ladd },
    { /* 98 */ "fadd", instr_fadd },
    { /* 99 */ "dadd", instr_dadd },
    { /* 100 */ "isub", instr_isub },
    { /* 101 */ "lsub", instr_lsub },
    { /* 102 */ "fsub", instr_fsub },
    { /* 103 */ "dsub", instr_dsub },
    { /* 104 */ "imul", instr_imul },
    { /* 105 */ "lmul", instr_lmul },
    { /* 106 */ "fmul", instr_fmul },
    { /* 107 */ "dmul", instr_dmul },
    { /* 108 */ "idiv", instr_idiv },
    { /* 109 */ "ldiv", instr_ldiv },
    { /* 110 */ "fdiv", instr_fdiv },
    { /* 111 */ "ddiv", instr_ddiv },
    { /* 112 */ "irem", instr_irem },
    { /* 113 */ "lrem", instr_lrem },
    { /* 114 */ "frem", instr_frem },
    { /* 115 */ "drem", instr_drem },
    { /* 116 */ "ineg", instr_ineg },
    { /* 117 */ "lneg", instr_lneg },
    { /* 118 */ "fneg", instr_fneg },
    { /* 119 */ "dneg", instr_dneg },
    { /* 120 */ "ishl", instr_ishl },
    { /* 121 */ "lshl", instr_lshl },
    { /* 122 */ "ishr", instr_ishr },
    { /* 123 */ "lshr", instr_lshr },
    { /* 124 */ "iushr", instr_iushr },
    { /* 125 */ "lushr", instr_lushr },
    { /* 126 */ "iand", instr_iand },
    { /* 127 */ "land", instr_land },
    { /* 128 */ "ior", instr_ior },
    { /* 129 */ "lor", instr_lor },
    { /* 130 */ "ixor", instr_ixor },
    { /* 131 */ "lxor", instr_lxor },
    { /* 132 */ "iinc", instr_iinc },
    { /* 133 */ "i2l", instr_i2l },
    { /* 134 */ "i2f", instr_i2f },
    { /* 135 */ "i2d", instr_i2d },
    { /* 136 */ "l2i", instr_l2i },
    { /* 137 */ "l2f", instr_l2f },
    { /* 138 */ "l2d", instr_l2d },
    { /* 139 */ "f2i", instr_f2i },
    { /* 140 */ "f2l", instr_f2l },
    { /* 141 */ "f2d", instr_f2d },
    { /* 142 */ "d2i", instr_d2i },
    { /* 143 */ "d2l", instr_d2l },
    { /* 144 */ "d2f", instr_d2f },
    { /* 145 */ "i2b", instr_i2b },
    { /* 146 */ "i2c", instr_i2c },
    { /* 147 */ "i2s", instr_i2s },
    { /* 148 */ "lcmp", instr_lcmp },
    { /* 149 */ "fcmpl", instr_fcmpl },
    { /* 150 */ "fcmpg", instr_fcmpg },
    { /* 151 */ "dcmpl", instr_dcmpl },
    { /* 152 */ "dcmpg", instr_dcmpg },
    { /* 153 */ "ifeq", instr_ifeq },
    { /* 154 */ "ifne", instr_ifne },
    { /* 155 */ "iflt", instr_iflt },
    { /* 156 */ "ifge", instr_ifge },
    { /* 157 */ "ifgt", instr_ifgt },
    { /* 158 */ "ifle", instr_ifle },
    { /* 159 */ "if_icmpeq", instr_if_icmpeq },
    { /* 160 */ "if_icmpne", instr_if_icmpne },
    { /* 161 */ "if_icmplt", instr_if_icmplt },
    { /* 162 */ "if_icmpge", instr_if_icmpge },
    { /* 163 */ "if_icmpgt", instr_if_icmpgt },
    { /* 164 */ "if_icmple", instr_if_icmple },
    { /* 165 */ "if_acmpeq", instr_if_acmpeq },
    { /* 166 */ "if_acmpne", instr_if_acmpne },
    { /* 167 */ "goto", instr_goto },
    { /* 168 */ "jsr", instr_jsr },
    { /* 169 */ "ret", instr_ret },
    { /* 170 */ "tableswitch", instr_tableswitch },
    { /* 171 */ "lookupswitch", instr_lookupswitch },
    { /* 172 */ "ireturn", instr_ireturn },
    { /* 173 */ "lreturn", instr_lreturn },
    { /* 174 */ "freturn", instr_freturn },
    { /* 175 */ "dreturn", instr_dreturn },
    { /* 176 */ "areturn", instr_areturn },
    { /* 177 */ "return", instr_return },
    { /* 178 */ "getstatic", instr_getstatic },
    { /* 179 */ "putstatic", instr_putstatic },
    { /* 180 */ "getfield", instr_getfield },
    { /* 181 */ "putfield", instr_putfield },
    { /* 182 */ "invokevirtual", instr_invokevirtual },
    { /* 183 */ "invokespecial", instr_invokespecial },
    { /* 184 */ "invokestatic", instr_invokestatic },
    { /* 185 */ "invokeinterface", instr_invokeinterface },
    { /* 186 */ "--unknown--", 0 },
    { /* 187 */ "new", instr_new },
    { /* 188 */ "newarray", instr_newarray },
    { /* 189 */ "anewarray", instr_anewarray },
    { /* 190 */ "arraylength", instr_arraylength },
    { /* 191 */ "athrow", instr_athrow },
    { /* 192 */ "checkcast", instr_checkcast },
    { /* 193 */ "instanceof", instr_instanceof },
    { /* 194 */ "monitorenter", instr_monitorenter },
    { /* 195 */ "monitorexit", instr_monitorexit },
    { /* 196 */ "wide", instr_wide },
    { /* 197 */ "multianewarray", instr_multianewarray },
    { /* 198 */ "ifnull", instr_ifnull },
    { /* 199 */ "ifnonnull", instr_ifnonnull },
    { /* 200 */ "goto_w", instr_goto_w },
    { /* 201 */ "jsr_w", instr_jsr_w },
