/* XXX AUTOMATICALLY GENERATED FILE -- DO NOT EDIT */
/* 0 */ static int instr_nop(water_JNIEnv *wenv);
/* 1 */ static int instr_aconst_null(water_JNIEnv *wenv);
/* 2 */ static int instr_iconst_m1(water_JNIEnv *wenv);
/* 3 */ static int instr_iconst_0(water_JNIEnv *wenv);
/* 4 */ static int instr_iconst_1(water_JNIEnv *wenv);
/* 5 */ static int instr_iconst_2(water_JNIEnv *wenv);
/* 6 */ static int instr_iconst_3(water_JNIEnv *wenv);
/* 7 */ static int instr_iconst_4(water_JNIEnv *wenv);
/* 8 */ static int instr_iconst_5(water_JNIEnv *wenv);
/* 9 */ static int instr_lconst_0(water_JNIEnv *wenv);
/* 10 */ static int instr_lconst_1(water_JNIEnv *wenv);
/* 11 */ static int instr_fconst_0(water_JNIEnv *wenv);
/* 12 */ static int instr_fconst_1(water_JNIEnv *wenv);
/* 13 */ static int instr_fconst_2(water_JNIEnv *wenv);
/* 14 */ static int instr_dconst_0(water_JNIEnv *wenv);
/* 15 */ static int instr_dconst_1(water_JNIEnv *wenv);
/* 16 */ static int instr_bipush(water_JNIEnv *wenv);
/* 17 */ static int instr_sipush(water_JNIEnv *wenv);
/* 18 */ static int instr_ldc(water_JNIEnv *wenv);
/* 19 */ static int instr_ldc_w(water_JNIEnv *wenv);
/* 20 */ static int instr_ldc2_w(water_JNIEnv *wenv);
/* 21 */ static int instr_iload(water_JNIEnv *wenv);
/* 22 */ static int instr_lload(water_JNIEnv *wenv);
/* 23 */ static int instr_fload(water_JNIEnv *wenv);
/* 24 */ static int instr_dload(water_JNIEnv *wenv);
/* 25 */ static int instr_aload(water_JNIEnv *wenv);
/* 26 */ static int instr_iload_0(water_JNIEnv *wenv);
/* 27 */ static int instr_iload_1(water_JNIEnv *wenv);
/* 28 */ static int instr_iload_2(water_JNIEnv *wenv);
/* 29 */ static int instr_iload_3(water_JNIEnv *wenv);
/* 30 */ static int instr_lload_0(water_JNIEnv *wenv);
/* 31 */ static int instr_lload_1(water_JNIEnv *wenv);
/* 32 */ static int instr_lload_2(water_JNIEnv *wenv);
/* 33 */ static int instr_lload_3(water_JNIEnv *wenv);
/* 34 */ static int instr_fload_0(water_JNIEnv *wenv);
/* 35 */ static int instr_fload_1(water_JNIEnv *wenv);
/* 36 */ static int instr_fload_2(water_JNIEnv *wenv);
/* 37 */ static int instr_fload_3(water_JNIEnv *wenv);
/* 38 */ static int instr_dload_0(water_JNIEnv *wenv);
/* 39 */ static int instr_dload_1(water_JNIEnv *wenv);
/* 40 */ static int instr_dload_2(water_JNIEnv *wenv);
/* 41 */ static int instr_dload_3(water_JNIEnv *wenv);
/* 42 */ static int instr_aload_0(water_JNIEnv *wenv);
/* 43 */ static int instr_aload_1(water_JNIEnv *wenv);
/* 44 */ static int instr_aload_2(water_JNIEnv *wenv);
/* 45 */ static int instr_aload_3(water_JNIEnv *wenv);
/* 46 */ static int instr_iaload(water_JNIEnv *wenv);
/* 47 */ static int instr_laload(water_JNIEnv *wenv);
/* 48 */ static int instr_faload(water_JNIEnv *wenv);
/* 49 */ static int instr_daload(water_JNIEnv *wenv);
/* 50 */ static int instr_aaload(water_JNIEnv *wenv);
/* 51 */ static int instr_baload(water_JNIEnv *wenv);
/* 52 */ static int instr_caload(water_JNIEnv *wenv);
/* 53 */ static int instr_saload(water_JNIEnv *wenv);
/* 54 */ static int instr_istore(water_JNIEnv *wenv);
/* 55 */ static int instr_lstore(water_JNIEnv *wenv);
/* 56 */ static int instr_fstore(water_JNIEnv *wenv);
/* 57 */ static int instr_dstore(water_JNIEnv *wenv);
/* 58 */ static int instr_astore(water_JNIEnv *wenv);
/* 59 */ static int instr_istore_0(water_JNIEnv *wenv);
/* 60 */ static int instr_istore_1(water_JNIEnv *wenv);
/* 61 */ static int instr_istore_2(water_JNIEnv *wenv);
/* 62 */ static int instr_istore_3(water_JNIEnv *wenv);
/* 63 */ static int instr_lstore_0(water_JNIEnv *wenv);
/* 64 */ static int instr_lstore_1(water_JNIEnv *wenv);
/* 65 */ static int instr_lstore_2(water_JNIEnv *wenv);
/* 66 */ static int instr_lstore_3(water_JNIEnv *wenv);
/* 67 */ static int instr_fstore_0(water_JNIEnv *wenv);
/* 68 */ static int instr_fstore_1(water_JNIEnv *wenv);
/* 69 */ static int instr_fstore_2(water_JNIEnv *wenv);
/* 70 */ static int instr_fstore_3(water_JNIEnv *wenv);
/* 71 */ static int instr_dstore_0(water_JNIEnv *wenv);
/* 72 */ static int instr_dstore_1(water_JNIEnv *wenv);
/* 73 */ static int instr_dstore_2(water_JNIEnv *wenv);
/* 74 */ static int instr_dstore_3(water_JNIEnv *wenv);
/* 75 */ static int instr_astore_0(water_JNIEnv *wenv);
/* 76 */ static int instr_astore_1(water_JNIEnv *wenv);
/* 77 */ static int instr_astore_2(water_JNIEnv *wenv);
/* 78 */ static int instr_astore_3(water_JNIEnv *wenv);
/* 79 */ static int instr_iastore(water_JNIEnv *wenv);
/* 80 */ static int instr_lastore(water_JNIEnv *wenv);
/* 81 */ static int instr_fastore(water_JNIEnv *wenv);
/* 82 */ static int instr_dastore(water_JNIEnv *wenv);
/* 83 */ static int instr_aastore(water_JNIEnv *wenv);
/* 84 */ static int instr_bastore(water_JNIEnv *wenv);
/* 85 */ static int instr_castore(water_JNIEnv *wenv);
/* 86 */ static int instr_sastore(water_JNIEnv *wenv);
/* 87 */ static int instr_pop(water_JNIEnv *wenv);
/* 88 */ static int instr_pop2(water_JNIEnv *wenv);
/* 89 */ static int instr_dup(water_JNIEnv *wenv);
/* 90 */ static int instr_dup_x1(water_JNIEnv *wenv);
/* 91 */ static int instr_dup_x2(water_JNIEnv *wenv);
/* 92 */ static int instr_dup2(water_JNIEnv *wenv);
/* 93 */ static int instr_dup2_x1(water_JNIEnv *wenv);
/* 94 */ static int instr_dup2_x2(water_JNIEnv *wenv);
/* 95 */ static int instr_swap(water_JNIEnv *wenv);
/* 96 */ static int instr_iadd(water_JNIEnv *wenv);
/* 97 */ static int instr_ladd(water_JNIEnv *wenv);
/* 98 */ static int instr_fadd(water_JNIEnv *wenv);
/* 99 */ static int instr_dadd(water_JNIEnv *wenv);
/* 100 */ static int instr_isub(water_JNIEnv *wenv);
/* 101 */ static int instr_lsub(water_JNIEnv *wenv);
/* 102 */ static int instr_fsub(water_JNIEnv *wenv);
/* 103 */ static int instr_dsub(water_JNIEnv *wenv);
/* 104 */ static int instr_imul(water_JNIEnv *wenv);
/* 105 */ static int instr_lmul(water_JNIEnv *wenv);
/* 106 */ static int instr_fmul(water_JNIEnv *wenv);
/* 107 */ static int instr_dmul(water_JNIEnv *wenv);
/* 108 */ static int instr_idiv(water_JNIEnv *wenv);
/* 109 */ static int instr_ldiv(water_JNIEnv *wenv);
/* 110 */ static int instr_fdiv(water_JNIEnv *wenv);
/* 111 */ static int instr_ddiv(water_JNIEnv *wenv);
/* 112 */ static int instr_irem(water_JNIEnv *wenv);
/* 113 */ static int instr_lrem(water_JNIEnv *wenv);
/* 114 */ static int instr_frem(water_JNIEnv *wenv);
/* 115 */ static int instr_drem(water_JNIEnv *wenv);
/* 116 */ static int instr_ineg(water_JNIEnv *wenv);
/* 117 */ static int instr_lneg(water_JNIEnv *wenv);
/* 118 */ static int instr_fneg(water_JNIEnv *wenv);
/* 119 */ static int instr_dneg(water_JNIEnv *wenv);
/* 120 */ static int instr_ishl(water_JNIEnv *wenv);
/* 121 */ static int instr_lshl(water_JNIEnv *wenv);
/* 122 */ static int instr_ishr(water_JNIEnv *wenv);
/* 123 */ static int instr_lshr(water_JNIEnv *wenv);
/* 124 */ static int instr_iushr(water_JNIEnv *wenv);
/* 125 */ static int instr_lushr(water_JNIEnv *wenv);
/* 126 */ static int instr_iand(water_JNIEnv *wenv);
/* 127 */ static int instr_land(water_JNIEnv *wenv);
/* 128 */ static int instr_ior(water_JNIEnv *wenv);
/* 129 */ static int instr_lor(water_JNIEnv *wenv);
/* 130 */ static int instr_ixor(water_JNIEnv *wenv);
/* 131 */ static int instr_lxor(water_JNIEnv *wenv);
/* 132 */ static int instr_iinc(water_JNIEnv *wenv);
/* 133 */ static int instr_i2l(water_JNIEnv *wenv);
/* 134 */ static int instr_i2f(water_JNIEnv *wenv);
/* 135 */ static int instr_i2d(water_JNIEnv *wenv);
/* 136 */ static int instr_l2i(water_JNIEnv *wenv);
/* 137 */ static int instr_l2f(water_JNIEnv *wenv);
/* 138 */ static int instr_l2d(water_JNIEnv *wenv);
/* 139 */ static int instr_f2i(water_JNIEnv *wenv);
/* 140 */ static int instr_f2l(water_JNIEnv *wenv);
/* 141 */ static int instr_f2d(water_JNIEnv *wenv);
/* 142 */ static int instr_d2i(water_JNIEnv *wenv);
/* 143 */ static int instr_d2l(water_JNIEnv *wenv);
/* 144 */ static int instr_d2f(water_JNIEnv *wenv);
/* 145 */ static int instr_i2b(water_JNIEnv *wenv);
/* 146 */ static int instr_i2c(water_JNIEnv *wenv);
/* 147 */ static int instr_i2s(water_JNIEnv *wenv);
/* 148 */ static int instr_lcmp(water_JNIEnv *wenv);
/* 149 */ static int instr_fcmpl(water_JNIEnv *wenv);
/* 150 */ static int instr_fcmpg(water_JNIEnv *wenv);
/* 151 */ static int instr_dcmpl(water_JNIEnv *wenv);
/* 152 */ static int instr_dcmpg(water_JNIEnv *wenv);
/* 153 */ static int instr_ifeq(water_JNIEnv *wenv);
/* 154 */ static int instr_ifne(water_JNIEnv *wenv);
/* 155 */ static int instr_iflt(water_JNIEnv *wenv);
/* 156 */ static int instr_ifge(water_JNIEnv *wenv);
/* 157 */ static int instr_ifgt(water_JNIEnv *wenv);
/* 158 */ static int instr_ifle(water_JNIEnv *wenv);
/* 159 */ static int instr_if_icmpeq(water_JNIEnv *wenv);
/* 160 */ static int instr_if_icmpne(water_JNIEnv *wenv);
/* 161 */ static int instr_if_icmplt(water_JNIEnv *wenv);
/* 162 */ static int instr_if_icmpge(water_JNIEnv *wenv);
/* 163 */ static int instr_if_icmpgt(water_JNIEnv *wenv);
/* 164 */ static int instr_if_icmple(water_JNIEnv *wenv);
/* 165 */ static int instr_if_acmpeq(water_JNIEnv *wenv);
/* 166 */ static int instr_if_acmpne(water_JNIEnv *wenv);
/* 167 */ static int instr_goto(water_JNIEnv *wenv);
/* 168 */ static int instr_jsr(water_JNIEnv *wenv);
/* 169 */ static int instr_ret(water_JNIEnv *wenv);
/* 170 */ static int instr_tableswitch(water_JNIEnv *wenv);
/* 171 */ static int instr_lookupswitch(water_JNIEnv *wenv);
/* 172 */ static int instr_ireturn(water_JNIEnv *wenv);
/* 173 */ static int instr_lreturn(water_JNIEnv *wenv);
/* 174 */ static int instr_freturn(water_JNIEnv *wenv);
/* 175 */ static int instr_dreturn(water_JNIEnv *wenv);
/* 176 */ static int instr_areturn(water_JNIEnv *wenv);
/* 177 */ static int instr_return(water_JNIEnv *wenv);
/* 178 */ static int instr_getstatic(water_JNIEnv *wenv);
/* 179 */ static int instr_putstatic(water_JNIEnv *wenv);
/* 180 */ static int instr_getfield(water_JNIEnv *wenv);
/* 181 */ static int instr_putfield(water_JNIEnv *wenv);
/* 182 */ static int instr_invokevirtual(water_JNIEnv *wenv);
/* 183 */ static int instr_invokespecial(water_JNIEnv *wenv);
/* 184 */ static int instr_invokestatic(water_JNIEnv *wenv);
/* 185 */ static int instr_invokeinterface(water_JNIEnv *wenv);
/* 187 */ static int instr_new(water_JNIEnv *wenv);
/* 188 */ static int instr_newarray(water_JNIEnv *wenv);
/* 189 */ static int instr_anewarray(water_JNIEnv *wenv);
/* 190 */ static int instr_arraylength(water_JNIEnv *wenv);
/* 191 */ static int instr_athrow(water_JNIEnv *wenv);
/* 192 */ static int instr_checkcast(water_JNIEnv *wenv);
/* 193 */ static int instr_instanceof(water_JNIEnv *wenv);
/* 194 */ static int instr_monitorenter(water_JNIEnv *wenv);
/* 195 */ static int instr_monitorexit(water_JNIEnv *wenv);
/* 196 */ static int instr_wide(water_JNIEnv *wenv);
/* 197 */ static int instr_multianewarray(water_JNIEnv *wenv);
/* 198 */ static int instr_ifnull(water_JNIEnv *wenv);
/* 199 */ static int instr_ifnonnull(water_JNIEnv *wenv);
/* 200 */ static int instr_goto_w(water_JNIEnv *wenv);
/* 201 */ static int instr_jsr_w(water_JNIEnv *wenv);
