/* XXX AUTOMATICALLY GENERATED FILE -- DO NOT EDIT */
	   case(0): instr_nop; break;
	   case(1): instr_aconst_null; break;
	   case(2): instr_iconst_m1; break;
	   case(3): instr_iconst_0; break;
	   case(4): instr_iconst_1; break;
	   case(5): instr_iconst_2; break;
	   case(6): instr_iconst_3; break;
	   case(7): instr_iconst_4; break;
	   case(8): instr_iconst_5; break;
	   case(9): instr_lconst_0; break;
	   case(10): instr_lconst_1; break;
	   case(11): instr_fconst_0; break;
	   case(12): instr_fconst_1; break;
	   case(13): instr_fconst_2; break;
	   case(14): instr_dconst_0; break;
	   case(15): instr_dconst_1; break;
	   case(16): instr_bipush; break;
	   case(17): instr_sipush; break;
	   case(18): instr_ldc; break;
	   case(19): instr_ldc_w; break;
	   case(20): instr_ldc2_w; break;
	   case(21): instr_iload; break;
	   case(22): instr_lload; break;
	   case(23): instr_fload; break;
	   case(24): instr_dload; break;
	   case(25): instr_aload; break;
	   case(26): instr_iload_0; break;
	   case(27): instr_iload_1; break;
	   case(28): instr_iload_2; break;
	   case(29): instr_iload_3; break;
	   case(30): instr_lload_0; break;
	   case(31): instr_lload_1; break;
	   case(32): instr_lload_2; break;
	   case(33): instr_lload_3; break;
	   case(34): instr_fload_0; break;
	   case(35): instr_fload_1; break;
	   case(36): instr_fload_2; break;
	   case(37): instr_fload_3; break;
	   case(38): instr_dload_0; break;
	   case(39): instr_dload_1; break;
	   case(40): instr_dload_2; break;
	   case(41): instr_dload_3; break;
	   case(42): instr_aload_0; break;
	   case(43): instr_aload_1; break;
	   case(44): instr_aload_2; break;
	   case(45): instr_aload_3; break;
	   case(46): instr_iaload; break;
	   case(47): instr_laload; break;
	   case(48): instr_faload; break;
	   case(49): instr_daload; break;
	   case(50): instr_aaload; break;
	   case(51): instr_baload; break;
	   case(52): instr_caload; break;
	   case(53): instr_saload; break;
	   case(54): instr_istore; break;
	   case(55): instr_lstore; break;
	   case(56): instr_fstore; break;
	   case(57): instr_dstore; break;
	   case(58): instr_astore; break;
	   case(59): instr_istore_0; break;
	   case(60): instr_istore_1; break;
	   case(61): instr_istore_2; break;
	   case(62): instr_istore_3; break;
	   case(63): instr_lstore_0; break;
	   case(64): instr_lstore_1; break;
	   case(65): instr_lstore_2; break;
	   case(66): instr_lstore_3; break;
	   case(67): instr_fstore_0; break;
	   case(68): instr_fstore_1; break;
	   case(69): instr_fstore_2; break;
	   case(70): instr_fstore_3; break;
	   case(71): instr_dstore_0; break;
	   case(72): instr_dstore_1; break;
	   case(73): instr_dstore_2; break;
	   case(74): instr_dstore_3; break;
	   case(75): instr_astore_0; break;
	   case(76): instr_astore_1; break;
	   case(77): instr_astore_2; break;
	   case(78): instr_astore_3; break;
	   case(79): instr_iastore; break;
	   case(80): instr_lastore; break;
	   case(81): instr_fastore; break;
	   case(82): instr_dastore; break;
	   case(83): instr_aastore; break;
	   case(84): instr_bastore; break;
	   case(85): instr_castore; break;
	   case(86): instr_sastore; break;
	   case(87): instr_pop; break;
	   case(88): instr_pop2; break;
	   case(89): instr_dup; break;
	   case(90): instr_dup_x1; break;
	   case(91): instr_dup_x2; break;
	   case(92): instr_dup2; break;
	   case(93): instr_dup2_x1; break;
	   case(94): instr_dup2_x2; break;
	   case(95): instr_swap; break;
	   case(96): instr_iadd; break;
	   case(97): instr_ladd; break;
	   case(98): instr_fadd; break;
	   case(99): instr_dadd; break;
	   case(100): instr_isub; break;
	   case(101): instr_lsub; break;
	   case(102): instr_fsub; break;
	   case(103): instr_dsub; break;
	   case(104): instr_imul; break;
	   case(105): instr_lmul; break;
	   case(106): instr_fmul; break;
	   case(107): instr_dmul; break;
	   case(108): instr_idiv; break;
	   case(109): instr_ldiv; break;
	   case(110): instr_fdiv; break;
	   case(111): instr_ddiv; break;
	   case(112): instr_irem; break;
	   case(113): instr_lrem; break;
	   case(114): instr_frem; break;
	   case(115): instr_drem; break;
	   case(116): instr_ineg; break;
	   case(117): instr_lneg; break;
	   case(118): instr_fneg; break;
	   case(119): instr_dneg; break;
	   case(120): instr_ishl; break;
	   case(121): instr_lshl; break;
	   case(122): instr_ishr; break;
	   case(123): instr_lshr; break;
	   case(124): instr_iushr; break;
	   case(125): instr_lushr; break;
	   case(126): instr_iand; break;
	   case(127): instr_land; break;
	   case(128): instr_ior; break;
	   case(129): instr_lor; break;
	   case(130): instr_ixor; break;
	   case(131): instr_lxor; break;
	   case(132): instr_iinc; break;
	   case(133): instr_i2l; break;
	   case(134): instr_i2f; break;
	   case(135): instr_i2d; break;
	   case(136): instr_l2i; break;
	   case(137): instr_l2f; break;
	   case(138): instr_l2d; break;
	   case(139): instr_f2i; break;
	   case(140): instr_f2l; break;
	   case(141): instr_f2d; break;
	   case(142): instr_d2i; break;
	   case(143): instr_d2l; break;
	   case(144): instr_d2f; break;
	   case(145): instr_i2b; break;
	   case(146): instr_i2c; break;
	   case(147): instr_i2s; break;
	   case(148): instr_lcmp; break;
	   case(149): instr_fcmpl; break;
	   case(150): instr_fcmpg; break;
	   case(151): instr_dcmpl; break;
	   case(152): instr_dcmpg; break;
	   case(153): instr_ifeq; break;
	   case(154): instr_ifne; break;
	   case(155): instr_iflt; break;
	   case(156): instr_ifge; break;
	   case(157): instr_ifgt; break;
	   case(158): instr_ifle; break;
	   case(159): instr_if_icmpeq; break;
	   case(160): instr_if_icmpne; break;
	   case(161): instr_if_icmplt; break;
	   case(162): instr_if_icmpge; break;
	   case(163): instr_if_icmpgt; break;
	   case(164): instr_if_icmple; break;
	   case(165): instr_if_acmpeq; break;
	   case(166): instr_if_acmpne; break;
	   case(167): instr_goto; break;
	   case(168): instr_jsr; break;
	   case(169): instr_ret; break;
	   case(170): instr_tableswitch; break;
	   case(171): instr_lookupswitch; break;
	   case(172): instr_ireturn; break;
	   case(173): instr_lreturn; break;
	   case(174): instr_freturn; break;
	   case(175): instr_dreturn; break;
	   case(176): instr_areturn; break;
	   case(177): instr_return; break;
	   case(178): instr_getstatic; break;
	   case(179): instr_putstatic; break;
	   case(180): instr_getfield; break;
	   case(181): instr_putfield; break;
	   case(182): instr_invokevirtual; break;
	   case(183): instr_invokespecial; break;
	   case(184): instr_invokestatic; break;
	   case(185): instr_invokeinterface; break;
	   case(187): instr_new; break;
	   case(188): instr_newarray; break;
	   case(189): instr_anewarray; break;
	   case(190): instr_arraylength; break;
	   case(191): instr_athrow; break;
	   case(192): instr_checkcast; break;
	   case(193): instr_instanceof; break;
	   case(194): instr_monitorenter; break;
	   case(195): instr_monitorexit; break;
	   case(196): instr_wide; break;
	   case(197): instr_multianewarray; break;
	   case(198): instr_ifnull; break;
	   case(199): instr_ifnonnull; break;
	   case(200): instr_goto_w; break;
	   case(201): instr_jsr_w; break;
